PlanetProfile/BuildTest.py
PlanetProfile/GetConfig.py
PlanetProfile/Main.py
PlanetProfile/__init__.py
PlanetProfile/defaultConfig.py
PlanetProfile/install.py
PlanetProfile/reset.py
PlanetProfile/Default/__init__.py
PlanetProfile/Default/Ariel/PPAriel.py
PlanetProfile/Default/Ariel/inductionData/Be1xyz_Ariel_Voyager_AH5noMP.txt
PlanetProfile/Default/Callisto/PPCallisto.py
PlanetProfile/Default/Callisto/inductionData/Be1xyz_Callisto_Galileo_VIP4K1997noMP.txt
PlanetProfile/Default/Dione/PPDione.py
PlanetProfile/Default/Dione/inductionData/Be1xyz_Dione_Cassini_Cassini11plusnoMP.txt
PlanetProfile/Default/Enceladus/PPEnceladus.py
PlanetProfile/Default/Enceladus/inductionData/Be1xyz_Enceladus_Cassini_Cassini11plusnoMP.txt
PlanetProfile/Default/Europa/PPEuropa.py
PlanetProfile/Default/Europa/PPEuropaInductOgram.py
PlanetProfile/Default/Europa/inductionData/Be1xyz_Europa_Juno_JRM33C2020noMP.txt
PlanetProfile/Default/Europa/inductionData/EuropaShape_4piNormDepth.txt
PlanetProfile/Default/Ganymede/PPGanymede.py
PlanetProfile/Default/Ganymede/inductionData/Be1xyz_Ganymede_Juno_JRM33C2020noMP.txt
PlanetProfile/Default/Iapetus/PPIapetus.py
PlanetProfile/Default/Iapetus/inductionData/Be1xyz_Iapetus_Cassini_Cassini11plusnoMP.txt
PlanetProfile/Default/Io/PPIo.py
PlanetProfile/Default/Io/inductionData/Be1xyz_Io_Juno_JRM33C2020noMP.txt
PlanetProfile/Default/Mimas/PPMimas.py
PlanetProfile/Default/Mimas/inductionData/Be1xyz_Mimas_Cassini_Cassini11plusnoMP.txt
PlanetProfile/Default/Miranda/PPMiranda.py
PlanetProfile/Default/Miranda/inductionData/Be1xyz_Miranda_Voyager_AH5noMP.txt
PlanetProfile/Default/Oberon/PPOberon.py
PlanetProfile/Default/Oberon/inductionData/Be1xyz_Oberon_Voyager_AH5noMP.txt
PlanetProfile/Default/Pluto/PPPluto.py
PlanetProfile/Default/Rhea/PPRhea.py
PlanetProfile/Default/Rhea/inductionData/Be1xyz_Rhea_Cassini_Cassini11noMP.txt
PlanetProfile/Default/Rhea/inductionData/Be1xyz_Rhea_Cassini_Cassini11plusnoMP.txt
PlanetProfile/Default/Tethys/PPTethys.py
PlanetProfile-2.5.0.dist-info/LICENSE
PlanetProfile-2.5.0.dist-info/METADATA
PlanetProfile-2.5.0.dist-info/WHEEL
PlanetProfile-2.5.0.dist-info/top_level.txt
PlanetProfile-2.5.0.dist-info/RECORD
