Metadata-Version: 2.1
Name: PlanetProfile
Version: 2.5.0
Summary: Self-consistent geophysical models for large moons and ocean worlds
Home-page: https://github.com/vancesteven/PlanetProfile
Author: Marshall J. Styczinski
Author-email: itsmoosh@gmail.com
Project-URL: Bug tracker, https://github.com/vancesteven/PlanetProfile/issues
Project-URL: Publication, https://doi.org/10.1029/2022EA002748
Classifier: Programming Language :: Python :: 3.8
Classifier: License :: OSI Approved :: GNU General Public License v3 (GPLv3)
Classifier: Operating System :: OS Independent
License-File: LICENSE
Requires-Dist: numpy >=1.24.4
Requires-Dist: scipy >=1.11.4
Requires-Dist: mpmath >=1.3.0
Requires-Dist: matplotlib >=3.8.2
Requires-Dist: SeaFreeze >=0.9.6
Requires-Dist: MoonMag >=1.7.5
Requires-Dist: gsw >=3.6.16
Requires-Dist: spiceypy >=6.0.0
Requires-Dist: cmasher >=1.6.3
Requires-Dist: hdf5storage >=0.1.19
